geoluminate/__init__.py
geoluminate/admin.py
geoluminate/api.py
geoluminate/apps.py
geoluminate/conf/__init__.py
geoluminate/conf/backends/__init__.py
geoluminate/conf/backends/celery.py
geoluminate/conf/backends/storage.py
geoluminate/conf/local.py
geoluminate/conf/production.py
geoluminate/conf/settings/__init__.py
geoluminate/conf/settings/admin.py
geoluminate/conf/settings/api.py
geoluminate/conf/settings/authentication.py
geoluminate/conf/settings/cache.py
geoluminate/conf/settings/celery.py
geoluminate/conf/settings/cms.py
geoluminate/conf/settings/comments.py
geoluminate/conf/settings/configuration.py
geoluminate/conf/settings/database.py
geoluminate/conf/settings/email.py
geoluminate/conf/settings/general.py
geoluminate/conf/settings/invitations.py
geoluminate/conf/settings/language.py
geoluminate/conf/settings/lockdown.py
geoluminate/conf/settings/logging.py
geoluminate/conf/settings/security.py
geoluminate/conf/settings/seo.py
geoluminate/conf/settings/staticfiles.py
geoluminate/conf/settings/storage.py
geoluminate/conf/settings/thumbnailer.py
geoluminate/conf/setup.py
geoluminate/context_processors.py
geoluminate/contrib/__init__.py
geoluminate/contrib/admin/__init__.py
geoluminate/contrib/admin/apps.py
geoluminate/contrib/admin/mixins.py
geoluminate/contrib/admin/monkeypatch.py
geoluminate/contrib/admin/templates/admin/base.html
geoluminate/contrib/admin/templates/admin/base_site.html
geoluminate/contrib/admin/templates/admin/change_list_object_tools.html
geoluminate/contrib/admin/templates/admin/includes/fieldset.html
geoluminate/contrib/admin/templates/django_spaghetti/plate.html
geoluminate/contrib/admin/templates/jazzmin_translate/application.html
geoluminate/contrib/admin/templates/jazzmin_translate/base.html
geoluminate/contrib/admin/templates/jazzmin_translate/index.html
geoluminate/contrib/admin/templates/jazzmin_translate/language.html
geoluminate/contrib/admin/templates/postgres_metrics/table.html
geoluminate/contrib/admin/tests/__init__.py
geoluminate-0.0.2.dist-info/LICENSE
geoluminate-0.0.2.dist-info/METADATA
geoluminate-0.0.2.dist-info/WHEEL
geoluminate-0.0.2.dist-info/RECORD
