Metadata-Version: 2.1
Name: geoluminate
Version: 0.0.2
Summary: 
Home-page: https://github.com/Geoluminate/geoluminate
License: GPL-3.0-or-later
Keywords: research,database,research data management,open data,geoluminate,FAIR
Author: Sam Jennings
Author-email: samuel.scott.jennings@gmail.com
Requires-Python: >=3.8,<4.0
Classifier: Development Status :: 1 - Planning
Classifier: Framework :: Django :: 4.0
Classifier: Intended Audience :: Developers
Classifier: License :: OSI Approved :: BSD License
Classifier: License :: OSI Approved :: GNU General Public License v3 or later (GPLv3+)
Classifier: Natural Language :: English
Classifier: Programming Language :: Python :: 3
Classifier: Programming Language :: Python :: 3.8
Classifier: Programming Language :: Python :: 3.9
Classifier: Programming Language :: Python :: 3.10
Classifier: Programming Language :: Python :: 3.11
Classifier: Programming Language :: Python :: 3.10
Classifier: Programming Language :: Python :: 3.11
Classifier: Programming Language :: Python :: 3.8
Classifier: Programming Language :: Python :: 3.9
Requires-Dist: celery (>=5.2.7,<6.0.0)
Requires-Dist: crispy-bootstrap5 (>=0.7,<0.8)
Requires-Dist: dj-rest-auth (>=3.0.0,<4.0.0)
Requires-Dist: django-adminactions (>=2.0.0,<3.0.0)
Requires-Dist: django-allauth (>=0.53.1,<0.54.0)
Requires-Dist: django-celery-beat (>=2.5.0,<3.0.0)
Requires-Dist: django-cms (>=3.11.1,<4.0.0)
Requires-Dist: django-compressor (>=4.3.1,<5.0.0)
Requires-Dist: django-cors-headers (>=3.14.0,<4.0.0)
Requires-Dist: django-crispy-forms (>=2.0,<3.0)
Requires-Dist: django-dbbackup (>=4.0.2,<5.0.0)
Requires-Dist: django-environ (>=0.10.0,<0.11.0)
Requires-Dist: django-filer (>=2.2.4,<3.0.0)
Requires-Dist: django-filter (>=22.1,<23.0)
Requires-Dist: django-fluent-comments[threadedcomments] (>=3.0,<4.0)
Requires-Dist: django-htmx (>=1.14.0,<2.0.0)
Requires-Dist: django-import-export (>=3.1.0,<4.0.0)
Requires-Dist: django-invitations (>=2.0.0,<3.0.0)
Requires-Dist: django-jazzmin (>=2.6.0,<3.0.0)
Requires-Dist: django-laboratory (>=0.0.1,<0.0.2)
Requires-Dist: django-libsass (>=0.9,<0.10)
Requires-Dist: django-literature (>=0.1.2,<0.2.0)
Requires-Dist: django-lockdown (>=4.0.0,<5.0.0)
Requires-Dist: django-meta (>=2.1.0,<3.0.0)
Requires-Dist: django-model-utils (>=4.3.1,<5.0.0)
Requires-Dist: django-modeltranslation (>=0.18.9,<0.19.0)
Requires-Dist: django-nested-admin (>=4.0.2,<5.0.0)
Requires-Dist: django-pint (>=0.7.1,<0.8.0)
Requires-Dist: django-postgres-metrics (>=0.13.1,<0.14.0)
Requires-Dist: django-redis (>=5.2.0,<6.0.0)
Requires-Dist: django-rosetta (>=0.9.8,<0.10.0)
Requires-Dist: django-select2 (>=8.1.1,<9.0.0)
Requires-Dist: django-simple-menu (>=2.1.1,<3.0.0)
Requires-Dist: django-social-share (>=2.3.0,<3.0.0)
Requires-Dist: django-solo (>=2.0.0,<3.0.0)
Requires-Dist: django-spaghetti-and-meatballs (>=0.4.2,<0.5.0)
Requires-Dist: django-split-settings (>=1.2.0,<2.0.0)
Requires-Dist: django-storages (>=1.13.2,<2.0.0)
Requires-Dist: django-tellme (>=0.7.3,<0.8.0)
Requires-Dist: django-treebeard (<4.5)
Requires-Dist: django[argon2] (>=3.2)
Requires-Dist: djangocms-frontend (>=1.1.0,<2.0.0)
Requires-Dist: djangorestframework (>=3.14.0,<4.0.0)
Requires-Dist: djangorestframework-datatables-editor (>=0.3.3,<0.4.0)
Requires-Dist: djangorestframework-gis (>=1.0,<2.0)
Requires-Dist: drf-access-policy (>=1.5.0,<2.0.0)
Requires-Dist: drf-nested-routers (>=0.93.4,<0.94.0)
Requires-Dist: drf-orjson-renderer (>=1.7.1,<2.0.0)
Requires-Dist: drf-schema-adapter (>=3.0.6,<4.0.0)
Requires-Dist: drf-spectacular[sidecar] (>=0.26.1,<0.27.0)
Requires-Dist: flower (>=1.2.0,<2.0.0)
Requires-Dist: gunicorn (>=20.1.0,<21.0.0)
Requires-Dist: polib (>=1.2.0,<2.0.0)
Requires-Dist: psycopg2-binary (>=2.9.5,<3.0.0)
Requires-Dist: pyyaml (>=6.0,<7.0)
Requires-Dist: redis (>=4.5.2,<5.0.0)
Requires-Dist: sentry-sdk[django] (>=1.17.0,<2.0.0)
Requires-Dist: shortuuid (>=1.0.11,<2.0.0)
Requires-Dist: tldextract (>=3.4.0,<4.0.0)
Requires-Dist: whitenoise (>=6.4.0,<7.0.0)
